renderjson/__init__.py
renderjson/main.py
renderjson-0.1.0.dist-info/entry_points.txt
renderjson-0.1.0.dist-info/WHEEL
renderjson-0.1.0.dist-info/METADATA
renderjson-0.1.0.dist-info/RECORD
